{
  "project_info": {
    "project_number": "305368040872",
    "firebase_url": "https://uicreserve-a8f8a.firebaseio.com",
    "project_id": "uicreserve-a8f8a",
    "storage_bucket": "uicreserve-a8f8a.appspot.com"
  },
  "client": [
    {
      "client_info": {
        "mobilesdk_app_id": "1:305368040872:android:7b6706c274caa2fd",
        "android_client_info": {
          "package_name": "com.uicreserve"
        }
      },
      "oauth_client": [
        {
          "client_id": "305368040872-fakev7pak4c85bhsk2jj8ide310mt1kd.apps.googleusercontent.com",
          "client_type": 3
        }
      ],
      "api_key": [
        {
          "current_key": "AIzaSyCNtaug57tJNHCsb2i-Td0kwBn2VqrcYBU"
        }
      ],
      "services": {
        "analytics_service": {
          "status": 1
        },
        "appinvite_service": {
          "status": 1,
          "other_platform_oauth_client": []
        },
        "ads_service": {
          "status": 2
        }
      }
    }
  ],
  "configuration_version": "1"
}